ZfileSDK/__init__.py
ZfileSDK/py.typed
ZfileSDK/admin/__init__.py
ZfileSDK/admin/direct_link_log_management.py
ZfileSDK/admin/direct_link_management.py
ZfileSDK/admin/ip_address_helper.py
ZfileSDK/admin/login_log_management.py
ZfileSDK/admin/login_module.py
ZfileSDK/admin/permission_module.py
ZfileSDK/admin/rule_management_upload_rules.py
ZfileSDK/admin/rule_management_view_rules.py
ZfileSDK/admin/rule_matcher_helper.py
ZfileSDK/admin/single_sign_on_management.py
ZfileSDK/admin/site_setting_module.py
ZfileSDK/admin/storage_source_module_basic.py
ZfileSDK/admin/storage_source_module_filter_file.py
ZfileSDK/admin/storage_source_module_metadata.py
ZfileSDK/admin/storage_source_module_permission.py
ZfileSDK/admin/storage_source_module_readme.py
ZfileSDK/admin/user_management.py
ZfileSDK/front/__init__.py
ZfileSDK/front/direct_short_chain_module.py
ZfileSDK/front/file_list_module.py
ZfileSDK/front/file_operation_module.py
ZfileSDK/front/gd_tools_assistive_module.py
ZfileSDK/front/initialization_module.py
ZfileSDK/front/onedrive_authentication_callback_module.py
ZfileSDK/front/oneonefive_tools_assistive_module.py
ZfileSDK/front/onlyoffice_related_interfaces.py
ZfileSDK/front/open_115_url_controller.py
ZfileSDK/front/s3_tools_assistive_module.py
ZfileSDK/front/server_proxy_download.py
ZfileSDK/front/server_proxy_upload.py
ZfileSDK/front/sharepoint_tools_assistive_module.py
ZfileSDK/front/short_link.py
ZfileSDK/front/single_sign_on.py
ZfileSDK/front/single_sign_on_interface.py
ZfileSDK/front/site_basic_module.py
ZfileSDK/front/user_interface.py
ZfileSDK/utils/__init__.py
ZfileSDK/utils/api_client.py
ZfileSDK/utils/base.py
ZfileSDK/utils/exceptions.py
ZfileSDK/utils/logger.py
ZfileSDK/utils/models.py
zfile_pysdk-1.1.1.dist-info/METADATA
zfile_pysdk-1.1.1.dist-info/WHEEL
zfile_pysdk-1.1.1.dist-info/top_level.txt
zfile_pysdk-1.1.1.dist-info/RECORD
