Metadata-Version: 2.4
Name: zfile-pysdk
Version: 1.1.1
Summary: Python SDK for ZFile API - 功能完整的ZFile文件管理系统SDK
Home-page: https://github.com/cuckoo711/zfile_sdk
Author: cuckoo
Author-email: cuckoo <3038604221@qq.com>
Project-URL: Homepage, https://github.com/cuckoo711/zfile_sdk
Project-URL: Bug Tracker, https://github.com/cuckoo711/zfile_sdk/issues
Project-URL: Documentation, https://api.zfile.vip/
Project-URL: Source Code, https://github.com/cuckoo711/zfile_sdk
Keywords: zfile,file management,api,sdk,cloud storage,file sharing
Classifier: Development Status :: 4 - Beta
Classifier: Intended Audience :: Developers
Classifier: License :: OSI Approved :: MIT License
Classifier: Operating System :: OS Independent
Classifier: Programming Language :: Python :: 3
Classifier: Programming Language :: Python :: 3.10
Classifier: Programming Language :: Python :: 3.11
Classifier: Programming Language :: Python :: 3.12
Classifier: Programming Language :: Python :: 3.13
Classifier: Topic :: Software Development :: Libraries :: Python Modules
Classifier: Topic :: Internet :: WWW/HTTP :: Dynamic Content
Classifier: Topic :: System :: Filesystems
Classifier: Typing :: Typed
Requires-Python: >=3.10
Requires-Dist: requests~=2.32.4
Requires-Dist: pydantic~=2.11.7
Requires-Dist: urllib3~=2.5.0
Requires-Dist: setuptools~=80.3.1
Requires-Dist: requests-toolbelt~=1.0.0
Provides-Extra: dev
Requires-Dist: pytest>=6.0; extra == "dev"
Requires-Dist: pytest-cov>=2.0; extra == "dev"
Requires-Dist: black>=21.0; extra == "dev"
Requires-Dist: flake8>=3.8; extra == "dev"
Requires-Dist: mypy>=0.800; extra == "dev"
Provides-Extra: docs
Requires-Dist: sphinx>=4.0; extra == "docs"
Requires-Dist: sphinx-rtd-theme>=1.0; extra == "docs"
Dynamic: author
Dynamic: home-page
Dynamic: requires-python
